{
  "cookies": [
    {
      "name": "ph_phc_yJW1VjHGGwmCbbrtczfqqNxgBDbhlhOWcdzcIJEOTFE_posthog",
      "value": "%7B%22distinct_id%22%3A%22019b4c64-1623-734a-9c94-faa6c65fda96%22%2C%22%24sesid%22%3A%5B1766513189636%2C%22019b4c64-16d2-7108-9c0d-0074d464093c%22%2C1766513186514%5D%7D",
      "domain": "localhost",
      "path": "/",
      "expires": 1798049189,
      "httpOnly": false,
      "secure": false,
      "sameSite": "Lax"
    }
  ],
  "origins": [
    {
      "origin": "http://localhost:3000",
      "localStorage": [
        {
          "name": "ph_phc_yJW1VjHGGwmCbbrtczfqqNxgBDbhlhOWcdzcIJEOTFE_posthog",
          "value": "{\"distinct_id\":\"019b4c64-1623-734a-9c94-faa6c65fda96\",\"$sesid\":[1766513189636,\"019b4c64-16d2-7108-9c0d-0074d464093c\",1766513186514],\"$initialization_time\":\"2025-12-23T18:06:29.505Z\",\"$configured_session_timeout_ms\":1800000,\"$device_id\":\"019b4c64-1623-734a-9c94-faa6c65fda96\",\"$user_state\":\"anonymous\",\"$session_recording_remote_config\":{\"enabled\":true,\"endpoint\":\"/s/\",\"consoleLogRecordingEnabled\":true,\"recorderVersion\":\"v2\",\"sampleRate\":0.01,\"minimumDurationMilliseconds\":30000,\"linkedFlag\":null,\"networkPayloadCapture\":{\"capturePerformance\":{\"network_timing\":false,\"web_vitals\":true,\"web_vitals_allowed_metrics\":null}},\"masking\":null,\"urlTriggers\":[],\"scriptConfig\":{\"script\":\"posthog-recorder\"},\"urlBlocklist\":[],\"eventTriggers\":[],\"triggerMatchType\":null,\"canvasRecording\":{}},\"$autocapture_disabled_server_side\":true,\"$heatmaps_enabled_server_side\":false,\"$product_tours_enabled_server_side\":false,\"$web_vitals_enabled_server_side\":true,\"$web_vitals_allowed_metrics\":null,\"$exception_capture_enabled_server_side\":false,\"$error_tracking_suppression_rules\":[],\"$dead_clicks_enabled_server_side\":false,\"$active_feature_flags\":[],\"$enabled_feature_flags\":{},\"$feature_flag_payloads\":{},\"$feature_flag_details\":{},\"$feature_flag_request_id\":\"b1a68fd4-49b7-4ab3-a3e2-dc1d3e36072f\",\"$feature_flag_evaluated_at\":1766513189535,\"$client_session_props\":{\"sessionId\":\"019b4c64-16d2-7108-9c0d-0074d464093c\",\"props\":{\"r\":\"$direct\",\"u\":\"http://localhost:3000/login\"}},\"$session_is_sampled\":false}"
        },
        {
          "name": "admin_user",
          "value": "{\"id\":\"4056991c-8b58-4ea5-8ba4-091207c06a39\",\"tenant_id\":\"default_casino\",\"username\":\"superadmin\",\"email\":\"admin@casino.com\",\"full_name\":\"Super Owner\",\"role\":\"Super Admin\",\"tenant_role\":\"tenant_admin\",\"is_platform_owner\":true,\"status\":\"active\",\"is_active\":true,\"failed_login_attempts\":0,\"created_at\":\"2025-12-22T12:16:13.894919\"}"
        },
        {
          "name": "admin_token",
          "value": "eyJhbGciOiJIUzI1NiIsInR5cCI6IkpXVCJ9.eyJzdWIiOiI0MDU2OTkxYy04YjU4LTRlYTUtOGJhNC0wOTEyMDdjMDZhMzkiLCJlbWFpbCI6ImFkbWluQGNhc2luby5jb20iLCJ0ZW5hbnRfaWQiOiJkZWZhdWx0X2Nhc2lubyIsInJvbGUiOiJTdXBlciBBZG1pbiIsImV4cCI6MTc2NjU5OTU4OX0.N4ZvetLBKb8R2nhqMdsXIK4FNJFGgEVZKIYXk8dT2e8"
        }
      ]
    }
  ]
}